pyepgdb/__init__.py
pyepgdb/compression.py
pyepgdb/serialisation.py
pyepgdb/structure.py
pyepgdb/values.py
pyepgdb/_bytedata/__init__.py
pyepgdb/_bytedata/define.py
pyepgdb/_bytedata/parse.py
pyepgdb/_bytedata/result.py
pyepgdb/_bytedata/util.py
pyepgdb/network/__init__.py
pyepgdb/network/_util.py
pyepgdb/network/dvbtuk.py
test/__init__.py
test/integration/__init__.py
test/integration/core.py
test/integration/dvbtuk.py
test/integration/testutil.py
pyepgdb-1.2.0.dist-info/LICENSE
pyepgdb-1.2.0.dist-info/METADATA
pyepgdb-1.2.0.dist-info/WHEEL
pyepgdb-1.2.0.dist-info/top_level.txt
pyepgdb-1.2.0.dist-info/RECORD
