Metadata-Version: 2.1
Name: pyepgdb
Version: 1.2.0
Summary: Python library for parsing Tvheadend epgdb files
Home-page: http://ikn.org.uk/pyepgdb
Author: Joseph Lansdowne
Author-email: ikn@ikn.org.uk
License: UNKNOWN
Platform: UNKNOWN
Classifier: Programming Language :: Python :: 3.4
Classifier: License :: OSI Approved :: BSD License
Classifier: Operating System :: OS Independent
